[{"BLOCK":5,"QES":1,"type_alt1":"City","price_alt1":76.99,"stars_alt1":"**","rating_alt1":2.79,"distance_alt1":13.4,"type_alt2":"Nature","price_alt2":95.99,"stars_alt2":"****","rating_alt2":9.17,"distance_alt2":34.7},{"BLOCK":5,"QES":2,"type_alt1":"Nature","price_alt1":138.99,"stars_alt1":"****","rating_alt1":5,"distance_alt1":13.3,"type_alt2":"Nature","price_alt2":133.99,"stars_alt2":"****","rating_alt2":2.73,"distance_alt2":34.7},{"BLOCK":5,"QES":3,"type_alt1":"City","price_alt1":75.99,"stars_alt1":"****","rating_alt1":7.06,"distance_alt1":33.8,"type_alt2":"Nature","price_alt2":100.99,"stars_alt2":"****","rating_alt2":7.35,"distance_alt2":36.9},{"BLOCK":5,"QES":4,"type_alt1":"Beach","price_alt1":67.99,"stars_alt1":"**","rating_alt1":9.15,"distance_alt1":6.9,"type_alt2":"City","price_alt2":127.99,"stars_alt2":"**","rating_alt2":5.17,"distance_alt2":13.2}]
