[{"8_BLOCK":12,"8_QES":1,"8_type_alt1":"City","8_price_alt1":"112.99","8_stars_alt1":"**","8_rating_alt1":"4.6","8_distance_alt1":"46.7","8_type_alt2":"Beach","8_price_alt2":" 77.99","8_stars_alt2":"****","8_rating_alt2":"6.1","8_distance_alt2":"13.8","8_type_alt3":"Nature","8_price_alt3":"154.99","8_stars_alt3":"**","8_rating_alt3":"8.1","8_distance_alt3":"42.7","8_type_alt4":"City","8_price_alt4":"114.99","8_stars_alt4":"****","8_rating_alt4":"9.3","8_distance_alt4":"24.2","8_type_alt5":"Beach","8_price_alt5":" 77.99","8_stars_alt5":"**","8_rating_alt5":"4.8","8_distance_alt5":"31.6","8_type_alt6":"Nature","8_price_alt6":"140.99","8_stars_alt6":"****","8_rating_alt6":"6.4","8_distance_alt6":"16.5","8_type_alt7":"City","8_price_alt7":"104.99","8_stars_alt7":"**","8_rating_alt7":"7.6","8_distance_alt7":"30.6","8_type_alt8":"Beach","8_price_alt8":" 79.99","8_stars_alt8":"****","8_rating_alt8":"9.0","8_distance_alt8":"20.7"},{"8_BLOCK":12,"8_QES":2,"8_type_alt1":"City","8_price_alt1":"154.99","8_stars_alt1":"****","8_rating_alt1":"8.3","8_distance_alt1":" 5.6","8_type_alt2":"Beach","8_price_alt2":"119.99","8_stars_alt2":"**","8_rating_alt2":"4.7","8_distance_alt2":"37.5","8_type_alt3":"Nature","8_price_alt3":" 71.99","8_stars_alt3":"****","8_rating_alt3":"6.4","8_distance_alt3":"12.2","8_type_alt4":"City","8_price_alt4":"152.99","8_stars_alt4":"**","8_rating_alt4":"7.8","8_distance_alt4":"40.8","8_type_alt5":"Beach","8_price_alt5":"113.99","8_stars_alt5":"****","8_rating_alt5":"8.7","8_distance_alt5":" 7.3","8_type_alt6":"Nature","8_price_alt6":" 69.99","8_stars_alt6":"**","8_rating_alt6":"4.7","8_distance_alt6":"47.1","8_type_alt7":"City","8_price_alt7":"144.99","8_stars_alt7":"****","8_rating_alt7":"6.9","8_distance_alt7":" 7.9","8_type_alt8":"Beach","8_price_alt8":"109.99","8_stars_alt8":"**","8_rating_alt8":"7.1","8_distance_alt8":"43.5"},{"8_BLOCK":12,"8_QES":3,"8_type_alt1":"City","8_price_alt1":"120.99","8_stars_alt1":"****","8_rating_alt1":"7.9","8_distance_alt1":"15.7","8_type_alt2":"Beach","8_price_alt2":" 91.99","8_stars_alt2":"**","8_rating_alt2":"8.3","8_distance_alt2":"45.7","8_type_alt3":"Nature","8_price_alt3":"144.99","8_stars_alt3":"****","8_rating_alt3":"4.6","8_distance_alt3":"10.6","8_type_alt4":"City","8_price_alt4":" 99.99","8_stars_alt4":"**","8_rating_alt4":"6.9","8_distance_alt4":"44.6","8_type_alt5":"Beach","8_price_alt5":" 77.99","8_stars_alt5":"****","8_rating_alt5":"7.2","8_distance_alt5":" 8.9","8_type_alt6":"Nature","8_price_alt6":"142.99","8_stars_alt6":"**","8_rating_alt6":"9.5","8_distance_alt6":"38.7","8_type_alt7":"City","8_price_alt7":"105.99","8_stars_alt7":"****","8_rating_alt7":"4.7","8_distance_alt7":"19.4","8_type_alt8":"Beach","8_price_alt8":" 90.99","8_stars_alt8":"**","8_rating_alt8":"5.8","8_distance_alt8":"45.8"},{"8_BLOCK":12,"8_QES":4,"8_type_alt1":"City","8_price_alt1":"151.99","8_stars_alt1":"****","8_rating_alt1":"5.7","8_distance_alt1":"34.6","8_type_alt2":"Beach","8_price_alt2":" 97.99","8_stars_alt2":"**","8_rating_alt2":"6.2","8_distance_alt2":"18.4","8_type_alt3":"Nature","8_price_alt3":" 77.99","8_stars_alt3":"****","8_rating_alt3":"8.0","8_distance_alt3":"48.1","8_type_alt4":"City","8_price_alt4":"133.99","8_stars_alt4":"**","8_rating_alt4":"8.8","8_distance_alt4":" 6.7","8_type_alt5":"Beach","8_price_alt5":"114.99","8_stars_alt5":"****","8_rating_alt5":"5.6","8_distance_alt5":"32.3","8_type_alt6":"Nature","8_price_alt6":" 76.99","8_stars_alt6":"**","8_rating_alt6":"6.9","8_distance_alt6":" 8.5","8_type_alt7":"City","8_price_alt7":"149.99","8_stars_alt7":"****","8_rating_alt7":"7.2","8_distance_alt7":"42.8","8_type_alt8":"Beach","8_price_alt8":"105.99","8_stars_alt8":"**","8_rating_alt8":"8.6","8_distance_alt8":" 6.1"}]
